ajpack/__init__.py
ajpack/py.typed
ajpack/settings.py
ajpack/aes/__init__.py
ajpack/aes/aes256.py
ajpack/building/__init__.py
ajpack/building/builder.py
ajpack/checks/__init__.py
ajpack/checks/internet.py
ajpack/checks/vm.py
ajpack/ctk/__init__.py
ajpack/ctk/ctk.py
ajpack/ctk/questions.py
ajpack/data/__init__.py
ajpack/data/get_data.py
ajpack/decorators/__init__.py
ajpack/decorators/time.py
ajpack/destroy/__init__.py
ajpack/destroy/reg.py
ajpack/files/__init__.py
ajpack/files/search.py
ajpack/files/sync.py
ajpack/folder/__init__.py
ajpack/folder/env.py
ajpack/fun/__init__.py
ajpack/fun/destruct.py
ajpack/fun/jokes.py
ajpack/hack/__init__.py
ajpack/hack/keyboard.py
ajpack/hack/mouse.py
ajpack/hardware/__init__.py
ajpack/hardware/gpu.py
ajpack/hash/__init__.py
ajpack/hash/etag.py
ajpack/hash/hash.py
ajpack/os/__init__.py
ajpack/os/base_path.py
ajpack/os/batt.py
ajpack/os/disk.py
ajpack/os/folders.py
ajpack/os/get_drives.py
ajpack/os/kill.py
ajpack/os/network.py
ajpack/os/processes.py
ajpack/os/ressources.py
ajpack/os/uptime.py
ajpack/os/volume.py
ajpack/os/widget.py
ajpack/os/win.py
ajpack/pwd/__init__.py
ajpack/pwd/pwds.py
ajpack/rsa/__init__.py
ajpack/rsa/rsa.py
ajpack/schedule/__init__.py
ajpack/schedule/schedule.py
ajpack/send/__init__.py
ajpack/send/email.py
ajpack/send/send_data.py
ajpack/socket/__init__.py
ajpack/socket/connection.py
ajpack/terminal/__init__.py
ajpack/terminal/apps.py
ajpack/terminal/commands.py
ajpack/terminal/logging.py
ajpack/terminal/print.py
ajpack/test/__init__.py
ajpack/test/test.py
ajpack/time/__init__.py
ajpack/time/convert_time.py
ajpack/useful/__init__.py
ajpack/useful/convert.py
ajpack/useful/exception.py
ajpack/useful/format.py
ajpack/useful/language.py
ajpack/useful/music.py
ajpack/useful/notifications.py
ajpack/useful/shortcut.py
ajpack/useful/stripping.py
ajpack/useful/toggle.py
ajpack/useful/wait.py
ajpack/zip/__init__.py
ajpack/zip/zipping.py
ajpack-1.29.0.dist-info/METADATA
ajpack-1.29.0.dist-info/WHEEL
ajpack-1.29.0.dist-info/top_level.txt
ajpack-1.29.0.dist-info/RECORD
