Metadata-Version: 2.1
Name: ajpack
Version: 1.29.0
Summary: A simple module for windows which does some simple stuff. Don't make something illegal ;)  Join our discord channel: https://discord.gg/HvwFgC54UJ
Home-page: https://github.com/AJ-Holzer/AJ-Module
Author: AJ-Holzer
License: MIT
Requires-Dist: pyzipper
Requires-Dist: opencv-python
Requires-Dist: requests
Requires-Dist: Pillow
Requires-Dist: keyboard
Requires-Dist: pywin32
Requires-Dist: psutil
Requires-Dist: winshell
Requires-Dist: plyer
Requires-Dist: customtkinter
Requires-Dist: cryptography
Requires-Dist: pycryptodome
Requires-Dist: pygame
Requires-Dist: pynput
Requires-Dist: pystray
